pyartifactory/__init__.py
pyartifactory/exception.py
pyartifactory/models/__init__.py
pyartifactory/models/artifact.py
pyartifactory/models/auth.py
pyartifactory/models/build.py
pyartifactory/models/group.py
pyartifactory/models/permission.py
pyartifactory/models/repository.py
pyartifactory/models/user.py
pyartifactory/objects/__init__.py
pyartifactory/objects/artifact.py
pyartifactory/objects/artifactory.py
pyartifactory/objects/build.py
pyartifactory/objects/group.py
pyartifactory/objects/object.py
pyartifactory/objects/permission.py
pyartifactory/objects/repository.py
pyartifactory/objects/security.py
pyartifactory/objects/user.py
pyartifactory/py.typed
pyartifactory/utils.py
pyartifactory-2.11.2.dist-info/METADATA
pyartifactory-2.11.2.dist-info/WHEEL
pyartifactory-2.11.2.dist-info/licenses/LICENSE
pyartifactory-2.11.2.dist-info/RECORD
