Metadata-Version: 2.4
Name: PyArtifactory
Version: 2.11.2
Summary: Typed interactions with the Jfrog Artifactory REST API
License: MIT
License-File: LICENSE
Keywords: artifactory
Author: Ananias CARVALHO
Author-email: carvalhoananias@hotmail.com
Requires-Python: >=3.8,<4.0
Classifier: Development Status :: 5 - Production/Stable
Classifier: Intended Audience :: Developers
Classifier: Intended Audience :: System Administrators
Classifier: License :: OSI Approved :: MIT License
Classifier: Operating System :: OS Independent
Classifier: Programming Language :: Python :: 3
Classifier: Programming Language :: Python :: 3.8
Classifier: Programming Language :: Python :: 3.9
Classifier: Programming Language :: Python :: 3.10
Classifier: Programming Language :: Python :: 3.11
Classifier: Programming Language :: Python :: 3.12
Classifier: Programming Language :: Python :: 3.13
Classifier: Programming Language :: Python :: 3.14
Classifier: Topic :: Software Development :: Libraries
Classifier: Topic :: System :: Filesystems
Classifier: Typing :: Typed
Requires-Dist: pydantic[email] (>=2.4.0,<3.0.0)
Requires-Dist: requests (>=2.31,<3.0)
Requires-Dist: typing_extensions (>=4.7.1,<5.0.0)
Project-URL: Bug Tracker, https://github.com/anancarv/python-artifactory/issues
Project-URL: Documentation, https://github.com/anancarv/python-artifactory
Project-URL: Repository, https://github.com/anancarv/python-artifactory
